celery_redis_statedb/__init__.py
celery_redis_statedb/bootstep.py
celery_redis_statedb/state.py
celery_redis_statedb-0.1.0.dist-info/METADATA
celery_redis_statedb-0.1.0.dist-info/WHEEL
celery_redis_statedb-0.1.0.dist-info/licenses/LICENSE
celery_redis_statedb-0.1.0.dist-info/RECORD
