Metadata-Version: 2.4
Name: celery-redis-statedb
Version: 0.1.0
Summary: Redis-based statedb persistence for Celery workers
Project-URL: Homepage, https://github.com/slothyrulez/celery_redis_statedb
Project-URL: Repository, https://github.com/slothyrulez/celery_redis_statedb
Project-URL: Issues, https://github.com/slothyrulez/celery_redis_statedb/issues
Project-URL: Documentation, https://github.com/slothyrulez/celery_redis_statedb#readme
Author-email: Slothy Rules <slothyrulez@gmail.com>
License-Expression: BSD-3-Clause
License-File: LICENSE
Keywords: celery,distributed,persistence,redis,statedb,workers
Classifier: Development Status :: 4 - Beta
Classifier: Framework :: Celery
Classifier: Intended Audience :: Developers
Classifier: License :: OSI Approved :: BSD License
Classifier: Operating System :: OS Independent
Classifier: Programming Language :: Python :: 3
Classifier: Programming Language :: Python :: 3.10
Classifier: Programming Language :: Python :: 3.11
Classifier: Programming Language :: Python :: 3.12
Classifier: Programming Language :: Python :: 3.13
Classifier: Programming Language :: Python :: 3.14
Classifier: Topic :: Database
Classifier: Topic :: Software Development :: Libraries :: Python Modules
Classifier: Topic :: System :: Distributed Computing
Requires-Python: >=3.10
